mi_config/__init__.py
mi_config/config.py
mi_config/exceptions.py
mi_configurator-0.0.9.dist-info/LICENSE
mi_configurator-0.0.9.dist-info/METADATA
mi_configurator-0.0.9.dist-info/WHEEL
mi_configurator-0.0.9.dist-info/top_level.txt
mi_configurator-0.0.9.dist-info/RECORD
