Metadata-Version: 2.1
Name: mi-configurator
Version: 0.0.9
Summary: Model Integration app configuration management service
Author-email: Leon Starr <leon_starr@modelint.com>
License: MIT License
Project-URL: repository, https://github.com/modelint/mi_configurator
Project-URL: documentation, https://github.com/modelint/mi_configuratori/wiki
Keywords: 2D,draw,graphics,canvas,mbse,xuml,xtuml,sysml
Classifier: License :: OSI Approved :: MIT License
Classifier: Programming Language :: Python
Classifier: Programming Language :: Python :: 3
Requires-Python: >=3.12
License-File: LICENSE
Requires-Dist: PyYAML
Requires-Dist: tomli; python_version < "3.13"
Provides-Extra: build
Requires-Dist: build; extra == "build"
Requires-Dist: twine; extra == "build"
Provides-Extra: dev
Requires-Dist: bump2version; extra == "dev"
Requires-Dist: pytest; extra == "dev"
